six/__init__.py
six/schemas.py
six/six.py
six/middlewares/__init__.py
six/middlewares/encryption_middleware.py
six/middlewares/six_base_http_middleware.py
six/middlewares/six_independent_rate_limiter.py
six/middlewares/six_rate_limiter_middleware.py
six/utils/__init__.py
six/utils/encryption_utils.py
six/utils/time_utils.py
six_python/__init__.py
six_python/schemas.py
six_python/six.py
six_python/sixth_sense.py
six_python/middlewares/__init__.py
six_python/middlewares/encryption_middleware.py
six_python/middlewares/six_base_http_middleware.py
six_python/middlewares/six_independent_rate_limiter.py
six_python/middlewares/six_rate_limiter_middleware.py
six_python/utils/__init__.py
six_python/utils/encryption_utils.py
six_python/utils/time_utils.py
six_python-0.1.2.dist-info/LICENSE
six_python-0.1.2.dist-info/METADATA
six_python-0.1.2.dist-info/WHEEL
six_python-0.1.2.dist-info/top_level.txt
six_python-0.1.2.dist-info/RECORD
